RPALibrary/__init__.py
RPALibrary/deco.py
RPALibrary/exceptions.py
RPALibrary/helpers.py
RPALibrary/messages.py
RPALibrary/stages/BaseStage.py
RPALibrary/stages/Consumer.py
RPALibrary/stages/Producer.py
RPALibrary/stages/__init__.py
RPAListener/RPAListener.py
RPAListener/__init__.py
RPAListener/exceptions.py
RPAListener/helpers.py
rpadriver-1.4.0.dist-info/LICENSE
rpadriver-1.4.0.dist-info/METADATA
rpadriver-1.4.0.dist-info/WHEEL
rpadriver-1.4.0.dist-info/top_level.txt
rpadriver-1.4.0.dist-info/RECORD
