Metadata-Version: 2.2
Name: rpadriver
Version: 1.4.0
Summary: RPADriver: RPA helper library built on the TOS model using task-object-storage package.
Author-email: SKALER / Siili Solutions Oyj <skaler-support@siili.com>
License: Copyright 2019-2025 Siili Solutions Oyj
Project-URL: Homepage, https://pypi.org/project/rpadriver/
Classifier: Programming Language :: Python :: 3
Classifier: Operating System :: OS Independent
Classifier: Intended Audience :: Developers
Classifier: License :: OSI Approved :: Apache Software License
Requires-Python: >=3.9
License-File: LICENSE
Requires-Dist: task-object-storage~=1.2
Requires-Dist: packaging
Requires-Dist: Pillow>=9.3.0
